handy_archives/__init__.py
handy_archives/py.typed
handy_archives/testing.py
handy_archives-0.1.4.dist-info/LICENSE
handy_archives-0.1.4.dist-info/WHEEL
handy_archives-0.1.4.dist-info/METADATA
handy_archives-0.1.4.dist-info/RECORD
