Metadata-Version: 2.1
Name: handy-archives
Version: 0.1.4
Summary: Some handy archive helpers for Python.
Keywords: archive,shutil,tar,zip
Author-email: Dominic Davis-Foster <dominic@davis-foster.co.uk>
Requires-Python: >=3.6.1
Classifier: Development Status :: 4 - Beta
Classifier: Intended Audience :: Developers
Classifier: License :: OSI Approved :: MIT License
Classifier: Operating System :: OS Independent
Classifier: Programming Language :: Python
Classifier: Programming Language :: Python :: 3 :: Only
Classifier: Programming Language :: Python :: 3.6
Classifier: Programming Language :: Python :: 3.7
Classifier: Programming Language :: Python :: 3.8
Classifier: Programming Language :: Python :: 3.9
Classifier: Programming Language :: Python :: 3.10
Classifier: Programming Language :: Python :: Implementation :: CPython
Classifier: Programming Language :: Python :: Implementation :: PyPy
Classifier: Topic :: Software Development :: Libraries :: Python Modules
Classifier: Topic :: System :: Archiving
Classifier: Topic :: System :: Archiving :: Compression
Classifier: Typing :: Typed
Requires-Dist: coincidence>=0.2.0 ; extra == "all"
Requires-Dist: pytest>=6.0.0 ; extra == "all"
Requires-Dist: coincidence>=0.2.0 ; extra == "testing"
Requires-Dist: pytest>=6.0.0 ; extra == "testing"
Project-URL: Documentation, https://handy-archives.readthedocs.io/en/latest
Project-URL: Homepage, https://github.com/domdfcoding/handy-archives
Project-URL: Issue Tracker, https://github.com/domdfcoding/handy-archives/issues
Project-URL: Source Code, https://github.com/domdfcoding/handy-archives
Provides-Extra: all
Provides-Extra: testing
